{
	"cmake" : 
	{
		"generator" : 
		{
			"multiConfig" : false,
			"name" : "Ninja"
		},
		"paths" : 
		{
			"cmake" : "D:/softinstalled/CLion 2022.3.2/bin/cmake/win/x64/bin/cmake.exe",
			"cpack" : "D:/softinstalled/CLion 2022.3.2/bin/cmake/win/x64/bin/cpack.exe",
			"ctest" : "D:/softinstalled/CLion 2022.3.2/bin/cmake/win/x64/bin/ctest.exe",
			"root" : "D:/softinstalled/CLion 2022.3.2/bin/cmake/win/x64/share/cmake-3.24"
		},
		"version" : 
		{
			"isDirty" : false,
			"major" : 3,
			"minor" : 24,
			"patch" : 2,
			"string" : "3.24.2",
			"suffix" : ""
		}
	},
	"objects" : 
	[
		{
			"jsonFile" : "codemodel-v2-42d11503f51f4dc98724.json",
			"kind" : "codemodel",
			"version" : 
			{
				"major" : 2,
				"minor" : 4
			}
		},
		{
			"jsonFile" : "cache-v2-541a0ad2be57e103887f.json",
			"kind" : "cache",
			"version" : 
			{
				"major" : 2,
				"minor" : 0
			}
		},
		{
			"jsonFile" : "cmakeFiles-v1-35a62d2483d81e66343a.json",
			"kind" : "cmakeFiles",
			"version" : 
			{
				"major" : 1,
				"minor" : 0
			}
		},
		{
			"jsonFile" : "toolchains-v1-8a86fc4382fbe1f4f748.json",
			"kind" : "toolchains",
			"version" : 
			{
				"major" : 1,
				"minor" : 0
			}
		}
	],
	"reply" : 
	{
		"cache-v2" : 
		{
			"jsonFile" : "cache-v2-541a0ad2be57e103887f.json",
			"kind" : "cache",
			"version" : 
			{
				"major" : 2,
				"minor" : 0
			}
		},
		"cmakeFiles-v1" : 
		{
			"jsonFile" : "cmakeFiles-v1-35a62d2483d81e66343a.json",
			"kind" : "cmakeFiles",
			"version" : 
			{
				"major" : 1,
				"minor" : 0
			}
		},
		"codemodel-v2" : 
		{
			"jsonFile" : "codemodel-v2-42d11503f51f4dc98724.json",
			"kind" : "codemodel",
			"version" : 
			{
				"major" : 2,
				"minor" : 4
			}
		},
		"toolchains-v1" : 
		{
			"jsonFile" : "toolchains-v1-8a86fc4382fbe1f4f748.json",
			"kind" : "toolchains",
			"version" : 
			{
				"major" : 1,
				"minor" : 0
			}
		}
	}
}
